LICENSE.md
README.md
pyproject.toml
setup.py
sebbs/__init__.py
sebbs/change_detection.cpp
sebbs/change_detection.pyx
sebbs/csebbs.py
sebbs/median_filter.py
sebbs/utils.py
sebbs.egg-info/PKG-INFO
sebbs.egg-info/SOURCES.txt
sebbs.egg-info/dependency_links.txt
sebbs.egg-info/requires.txt
sebbs.egg-info/top_level.txt
tests/test_change_detection.py
tests/test_csebbs.py
tests/test_median_filter.py