Metadata-Version: 2.4
Name: sebbs
Version: 1.0.2
Summary: Sound Event Bounding Boxes
Home-page: https://github.com/merlresearch/sound_event_bounding_boxes
Author: Mitsubishi Electric Research Laboratories
Author-email: ebbers[at]merl[dot]com
License: AGPL-3.0
Keywords: sound event detection,polyphonic sound detection,post processing,change detection
Classifier: Development Status :: 3 - Alpha
Classifier: Intended Audience :: Developers
Classifier: Topic :: Software Development :: Build Tools
Classifier: Programming Language :: Python :: 3.9
Classifier: Programming Language :: Python :: 3.10
Classifier: Programming Language :: Python :: 3.11
Classifier: Programming Language :: Python :: 3.12
Classifier: Programming Language :: Python :: 3.13
Classifier: Programming Language :: Python :: 3.14
License-File: LICENSE.md
Requires-Dist: numpy
Requires-Dist: pandas
Requires-Dist: scipy
Requires-Dist: pathlib
Requires-Dist: sed_scores_eval_np2>=0.0.4
Requires-Dist: Cython
Provides-Extra: dev
Requires-Dist: check-manifest; extra == "dev"
Provides-Extra: test
Requires-Dist: coverage; extra == "test"
Requires-Dist: jupyter; extra == "test"
Requires-Dist: matplotlib; extra == "test"
Dynamic: author
Dynamic: author-email
Dynamic: classifier
Dynamic: description
Dynamic: description-content-type
Dynamic: home-page
Dynamic: keywords
Dynamic: license
Dynamic: license-file
Dynamic: provides-extra
Dynamic: requires-dist
Dynamic: summary
